[
    {
        "title": "Bohemian Rhapsody",
        "artist": "Queen",
        "genre": "Rock",
        "year": 1975
    },
    {
        "title": "Shape of You",
        "artist": "Ed Sheeran",
        "genre": "Pop",
        "year": 2017
    },
    {
        "title": "Rolling in the Deep",
        "artist": "Adele",
        "genre": "Soul",
        "year": 2010
    },
    {
        "title": "Smells Like Teen Spirit",
        "artist": "Nirvana",
        "genre": "Grunge",
        "year": 1991
    }
]